{
  "applicationId": "js.neutralino.sample",
  "port": 0,
  "defaultMode": "window",
  "enableHTTPServer": true,
  "enableNativeAPI": true,
  "url": "/resources/",
  "nativeBlockList": [],
  "globalVariables": {
    "TEST": "Test Value"
  },
  "modes": {
    "window": {
      "title": "walletjs",
      "width": 450,
      "height": 800,
      "fullScreen": false,
      "alwaysOnTop": false,
      "icon": "/resources/icons/wallet.png",
      "enableInspector": false,
      "borderless": true,
      "maximize": false
    },
    "browser": {},
    "cloud": {}
  },
  "cli": {
    "binaryName": "walletjs",
    "resourcesPath": "/resources/",
    "clientLibrary": "/resources/js/neutralino.js"
  }
}